llama_index/embeddings/huggingface_optimum/__init__.py
llama_index/embeddings/huggingface_optimum/base.py
llama_index_embeddings_huggingface_optimum-0.4.1.dist-info/METADATA
llama_index_embeddings_huggingface_optimum-0.4.1.dist-info/WHEEL
llama_index_embeddings_huggingface_optimum-0.4.1.dist-info/licenses/LICENSE
llama_index_embeddings_huggingface_optimum-0.4.1.dist-info/RECORD
